ecdf/__init__.py
ecdf-0.9.1.dist-info/licenses/LICENSE
ecdf-0.9.1.dist-info/WHEEL
ecdf-0.9.1.dist-info/METADATA
ecdf-0.9.1.dist-info/RECORD
