Metadata-Version: 2.4
Name: ecdf
Version: 0.9.1
Summary: Visualize dataframes with echarts
Author-email: Shel Kong <kongscn@gmail.com>
Requires-Python: >= 3.8
Classifier: Development Status :: 4 - Beta
Classifier: Intended Audience :: Developers
Classifier: License :: OSI Approved :: MIT License
Classifier: Programming Language :: Python :: 3
License-File: LICENSE
Requires-Dist: python-dateutil ~= 2.8
Requires-Dist: numpy
Requires-Dist: pandas
Requires-Dist: loguru
Requires-Dist: black ~= 25.1 ; extra == "dev"
Project-URL: Repository, https://github.com/kongscn/ecdf
Provides-Extra: dev
